xtquant/IPythonApiClient.cp36-win_amd64.pyd
xtquant/IPythonApiClient.cp37-win_amd64.pyd
xtquant/IPythonApiClient.cp38-win_amd64.pyd
xtquant/__init__.py
xtquant/libeay32.dll
xtquant/log4cxx.dll
xtquant/msvcp140.dll
xtquant/ssleay32.dll
xtquant/vcruntime140.dll
xtquant/xtconstant.py
xtquant/xtdata.ini
xtquant/xtdata.log4cxx
xtquant/xtdata.py
xtquant/xtpythonclient.cp36-win_amd64.pyd
xtquant/xtpythonclient.cp37-win_amd64.pyd
xtquant/xtpythonclient.cp38-win_amd64.pyd
xtquant/xttools.py
xtquant/xttrader.py
xtquant/xttype.py
xbx-0.1.9.dist-info/METADATA
xbx-0.1.9.dist-info/WHEEL
xbx-0.1.9.dist-info/top_level.txt
xbx-0.1.9.dist-info/RECORD
