Metadata-Version: 2.1
Name: xbx
Version: 0.1.9
Summary: xbx
Author: xbx
License: UNKNOWN
Platform: UNKNOWN
Requires-Dist: numpy (==1.22.4)
Requires-Dist: pandas (==1.5.3)
Requires-Dist: joblib (==1.3.2)
Requires-Dist: ccxt (==2.2.40)
Requires-Dist: dataframe-image (==0.1.5)
Requires-Dist: DrissionPage (==3.2.34)
Requires-Dist: lxml (==4.8.0)
Requires-Dist: ntplib (==0.4.0)
Requires-Dist: httpx (==0.26.0)
Requires-Dist: bs4 (==0.0.2)
Requires-Dist: tabulate (==0.8.9)
Requires-Dist: py-mini-racer (==0.6.0)
Requires-Dist: psutil (==5.9.6)
Requires-Dist: matplotlib (==3.7.2)
Requires-Dist: requests (==2.31.0)
Requires-Dist: tqdm (==4.66.1)
Requires-Dist: dash (==2.16.1)
Requires-Dist: dash-iconify (==0.1.2)
Requires-Dist: dash-mantine-components (==0.12.1)
Requires-Dist: plotly (==5.6.0)
Requires-Dist: pyarrow (==14.0.0)
Requires-Dist: retrying (==1.3.3)
Requires-Dist: scipy (==1.9.3)
Requires-Dist: scikit-learn (==1.3.0)
Requires-Dist: py7zr (==0.20.8)
Requires-Dist: rarfile (==4.0)
